MANIFEST.in
README
setup.py
IXWSAuth.egg-info/PKG-INFO
IXWSAuth.egg-info/SOURCES.txt
IXWSAuth.egg-info/dependency_links.txt
IXWSAuth.egg-info/requires.txt
IXWSAuth.egg-info/top_level.txt
ixwsauth_server/__init__.py
ixwsauth_server/models.py
ixwsauth_server/api/__init__.py
ixwsauth_server/api/rest_framework.py
ixwsauth_server/api/tastypie.py
ixwsauth_server/features/__init__.py
ixwsauth_server/features/steps/__init__.py
ixwsauth_server/middleware/__init__.py