Metadata-Version: 1.0
Name: IXWSAuth
Version: 1.0.0
Summary: Authentication libraries for IX web services
Home-page: http://pypi.python.org/pypi/IXWSAuth/
Author: Infoxchange dev team
Author-email: devs@infoxchange.org
License: MIT
Platform: UNKNOWN
